ssm_dotenv_config/__init__.py
ssm_dotenv_config-0.1.1.dist-info/LICENSE
ssm_dotenv_config-0.1.1.dist-info/WHEEL
ssm_dotenv_config-0.1.1.dist-info/METADATA
ssm_dotenv_config-0.1.1.dist-info/RECORD
