Metadata-Version: 2.1
Name: ssm-dotenv-config
Version: 0.1.1
Summary: 
Home-page: UNKNOWN
License: UNKNOWN
Author: Jared Lunde
Author-email: jared.lunde@gmail.com
Requires-Python: >=3.7,<4.0
Classifier: Programming Language :: Python :: 3
Classifier: Programming Language :: Python :: 3.7
Requires-Dist: boto3 (>=1.9,<2.0)
Requires-Dist: python-dotenv (>=0.10.2,<0.11.0)
Requires-Dist: ujson (>=1.35,<2.0)
Requires-Dist: vital-tools (>=0.1.13,<0.2.0)
